random_quote_generator/__init__.py
random_quote_generator/get_quote.py
random_quote_generator/quotes.py
vitari_random_quote_generator-0.1.0.dist-info/METADATA
vitari_random_quote_generator-0.1.0.dist-info/WHEEL
vitari_random_quote_generator-0.1.0.dist-info/RECORD
